LICENSE
MANIFEST.in
README.md
setup.py
clovaTTS/__init__.py
clovaTTS/clovaTTS.py
clovaTTS.egg-info/PKG-INFO
clovaTTS.egg-info/SOURCES.txt
clovaTTS.egg-info/dependency_links.txt
clovaTTS.egg-info/not-zip-safe
clovaTTS.egg-info/top_level.txt