Metadata-Version: 2.1
Name: clovaTTS
Version: 0.1.1
Summary: A TTS Wrapper for Naver Clova Speech Synthesis API
Home-page: https://github.com/zebehn/clovaTTS
Author: Minsu Jang
Author-email: minsu@etri.re.kr
License: MIT
Keywords: tts naver clova
Platform: UNKNOWN
Classifier: Development Status :: 2 - Pre-Alpha
Classifier: License :: OSI Approved :: MIT License
Classifier: Programming Language :: Python :: 3
